kyanitctl/__init__.py
kyanitctl/__main__.py
kyanitctl/_version.py
kyanitctl-1.1.0.dist-info/LICENSE
kyanitctl-1.1.0.dist-info/METADATA
kyanitctl-1.1.0.dist-info/WHEEL
kyanitctl-1.1.0.dist-info/entry_points.txt
kyanitctl-1.1.0.dist-info/top_level.txt
kyanitctl-1.1.0.dist-info/RECORD
