Metadata-Version: 2.1
Name: kyanitctl
Version: 1.1.0
Summary: Command-line utility for Kyanit
Home-page: https://github.com/kyanit-project/kyanitctl
Author: Zsolt Nagy
Author-email: zsolt@kyanit.eu
License: GPLv3
Platform: UNKNOWN
Classifier: Programming Language :: Python :: 3
Classifier: License :: OSI Approved :: GNU General Public License v3 (GPLv3)
Classifier: Intended Audience :: Developers
Classifier: Operating System :: OS Independent
Requires-Python: >=3.6
Requires-Dist: kyanitapi
